vpconfig/__init__.py
vpconfig/vpconfig.py
vpconfig-1.1.2.dist-info/METADATA
vpconfig-1.1.2.dist-info/WHEEL
vpconfig-1.1.2.dist-info/top_level.txt
vpconfig-1.1.2.dist-info/RECORD
